{"is_source_file": false, "format": "", "description": "", "external_files": [], "external_methods": [], "published": [], "classes": [], "methods": [], "calls": [], "search-terms": [], "state": 2, "file_id": 9, "knowledge_revision": 26, "git_revision": "e2cf342117370de4a558bf0a6d15d7b0d3db3fea", "hash": "d40a5d161946c7fa891d1f2352f3fe16", "format-version": 4, "code-base-name": "frontend_react_notes", "filename": "frontend_react_notes/README.md", "revision_history": [{"26": "e2cf342117370de4a558bf0a6d15d7b0d3db3fea"}]}